<collection xmlns="http://exist.sourceforge.net/NS/exist" name="/db/apps/monex/resources/DataTables-1.10.7" version="1" owner="monex" group="monex" mode="775" created="2019-12-21T08:35:27.699+01:00">
    <acl entries="0" version="1"/>
    <resource type="BinaryResource" name="Readme.md" skip="yes" owner="monex" group="monex" mode="664" created="2019-12-21T08:35:27.7+01:00" modified="2019-12-21T08:35:27.7+01:00" filename="Readme.md" mimetype="text/markdown">
        <acl entries="0" version="1"/>
    </resource>
    <resource type="BinaryResource" name="Contributing.md" skip="yes" owner="monex" group="monex" mode="664" created="2019-12-21T08:35:27.7+01:00" modified="2019-12-21T08:35:27.7+01:00" filename="Contributing.md" mimetype="text/markdown">
        <acl entries="0" version="1"/>
    </resource>
    <resource type="BinaryResource" name="license.txt" skip="yes" owner="monex" group="monex" mode="664" created="2019-12-21T08:35:27.701+01:00" modified="2019-12-21T08:35:27.701+01:00" filename="license.txt" mimetype="text/plain">
        <acl entries="0" version="1"/>
    </resource>
    <subcollection name="media" filename="media"/>
</collection>