<json><item><meta><numChildren>0</numChildren><createdByUser><name/><username>lindenberg</username><links><alternate><href>https://www.zotero.org/lindenberg</href><type>text/html</type></alternate></links><id>4.197265E6</id></createdByUser><creatorSummary>Thornton</creatorSummary><parsedDate>1867-12-01</parsedDate></meta><data><seriesTitle/><archive/><seriesText/><pages>S. 477-500 (I.), S. 592-602 (II.), S. 688-702(III.)</pages><journalAbbreviation/><ISSN/><creators><item><lastName>Thornton</lastName><creatorType>author</creatorType><firstName>W[illiam] T[homas]</firstName></item></creators><callNumber/><publicationTitle>The Fortnightly Review. London</publicationTitle><itemType>journalArticle</itemType><date>No. X. New Series. – October 1, 1867(I.); No. XI. New Series. – November 1, 1867(II:); No. XII. New Series. – December 1, 1867</date><url>http://opacplus.bsb-muenchen.de/title/9465331/ft/bsb10615196?page=7</url><extra>Alternativ: http://mdz-nbn-resolving.de/urn:nbn:de:bvb:12-bsb10615196-8 – Auch: https://babel.hathitrust.org/cgi/pt?id=inu.30000093208894&amp;view=1up&amp;seq=7</extra><dateAdded>2019-08-26T13:56:39Z</dateAdded><accessDate/><abstractNote/><collections/><dateModified>2019-08-26T14:49:20Z</dateModified><rights/><relations/><series/><archiveLocation/><version>7887</version><title>Stray Chapters From a Forthcomming Work on Labor. I. The Claims on Labour and its Rights. II. The Rights of Capital. III The Origin of Trades' Unions</title><language/><tags><item><tag>Briefjahrgang 1867</tag></item></tags><issue/><volume>Vol. II. New Series. July I, to December I, 1867 &lt;Vol. VIII. Old Series&gt;</volume><shortTitle/><DOI/><libraryCatalog/><key>5G29D83Z</key></data><version>7887</version><links><self><href>https://api.zotero.org/groups/604880/items/5G29D83Z</href><type>application/json</type></self><alternate><href>https://www.zotero.org/groups/mega/items/5G29D83Z</href><type>text/html</type></alternate></links><library><name>mega</name><links><alternate><href>https://www.zotero.org/groups/mega</href><type>text/html</type></alternate></links><type>group</type><id>604880</id></library><key>5G29D83Z</key></item></json>