<json><item><meta><numChildren>0</numChildren><createdByUser><name/><username>lindenberg</username><links><alternate><href>https://www.zotero.org/lindenberg</href><type>text/html</type></alternate></links><id>4.197265E6</id></createdByUser><creatorSummary>[Becker</creatorSummary><parsedDate>1866-01</parsedDate></meta><data><seriesTitle/><archive/><seriesText/><pages>S. 12-14</pages><journalAbbreviation/><ISSN/><creators><item><lastName>[Becker</lastName><creatorType>author</creatorType><firstName>Johann Philipp]</firstName></item></creators><callNumber/><publicationTitle>Der Vorbote. Genf</publicationTitle><itemType>journalArticle</itemType><date>Januar 1866</date><url/><extra/><dateAdded>2017-08-22T14:41:03Z</dateAdded><accessDate/><abstractNote/><collections/><dateModified>2019-06-18T14:36:06Z</dateModified><rights/><relations/><series/><archiveLocation/><version>7710</version><title>Die deutsche Abtheilung (aus Schweizern und Deutschen bestehend) …</title><language/><tags><item><tag>Briefjahrgang 1866</tag></item></tags><issue>Nr. 1</issue><volume>Jg. 1</volume><shortTitle/><DOI/><libraryCatalog/><key>8YR3KPJF</key></data><version>7710</version><links><self><href>https://api.zotero.org/groups/604880/items/8YR3KPJF</href><type>application/json</type></self><alternate><href>https://www.zotero.org/groups/mega/items/8YR3KPJF</href><type>text/html</type></alternate></links><library><name>mega</name><links><alternate><href>https://www.zotero.org/groups/mega</href><type>text/html</type></alternate></links><type>group</type><id>604880</id></library><key>8YR3KPJF</key></item></json>